citybussin/__init__.py
citybussin/citybussin.py
citybussin-0.0.1a3.dist-info/METADATA
citybussin-0.0.1a3.dist-info/WHEEL
citybussin-0.0.1a3.dist-info/RECORD
