Metadata-Version: 2.1
Name: citybussin
Version: 0.0.1a3
Summary: 
Author: Eric Park
Author-email: me@ericswpark.com
Requires-Python: >=3.12,<4.0
Classifier: Programming Language :: Python :: 3
Classifier: Programming Language :: Python :: 3.12
Requires-Dist: requests (>=2.32.3,<3.0.0)
